<?xml version="1.0" encoding="UTF-8"?>
<database>
    <element label="ECS Namespace Details" max_length="40" name="x_219618_ecs_dashb_ecs_namespace_details" type="collection">
        <element attributes="edge_encryption_enabled=true" label="allowedVPools" max_length="4000" name="allowedvpools" type="string"/>
        <element label="collectiontime" max_length="40" name="collectiontime" type="glide_date_time"/>
        <element label="defaultDataServicesVPool" max_length="1024" name="defaultdataservicesvpool" type="url"/>
        <element attributes="edge_encryption_enabled=true" label="disallowedVPools" max_length="4000" name="disallowedvpools" type="string"/>
        <element attributes="edge_encryption_enabled=true" label="externalGroupAdmins" max_length="40" name="externalgroupadmins" type="string"/>
        <element label="global" max_length="40" name="global" type="boolean"/>
        <element attributes="edge_encryption_enabled=true" label="id" max_length="125" name="id" type="string"/>
        <element label="inactive" max_length="40" name="inactive" type="boolean"/>
        <element label="internal" max_length="40" name="internal" type="boolean"/>
        <element label="isComplianceEnabled" max_length="40" name="iscomplianceenabled" type="boolean"/>
        <element label="isEncryptionEnabled" max_length="40" name="isencryptionenabled" type="boolean"/>
        <element label="isStaledAllowed" max_length="40" name="isstaledallowed" type="boolean"/>
        <element attributes="edge_encryption_enabled=true" label="link" max_length="1000" name="link" type="string"/>
        <element attributes="edge_encryption_enabled=true" label="name" max_length="1000" name="name" type="string"/>
        <element attributes="edge_encryption_enabled=true" label="namespaceAdmins" max_length="40" name="namespaceadmins" type="string"/>
        <element attributes="ignore_filter_on_new=true" default="javascript:global.getNextObjNumberPadded();" label="Number" max_length="40" name="number" type="string"/>
        <element label="remote" max_length="40" name="remote" type="boolean"/>
        <element attributes="edge_encryption_enabled=true" label="userMappings" max_length="40" name="usermappings" type="string"/>
        <element label="defaultBucketBlockSize" max_length="40" name="u_defaultbucketblocksize" type="longint"/>
        <element attributes="edge_encryption_enabled=true" label="vdc" max_length="4000" name="vdc" type="string"/>
    </element>
</database>
